logging_datetime/__init__.py
logging_datetime/logging_datetime.py
logging_datetime-1.1.9.data/scripts/logging_datetime.py
logging_datetime-1.1.9.dist-info/METADATA
logging_datetime-1.1.9.dist-info/WHEEL
logging_datetime-1.1.9.dist-info/top_level.txt
logging_datetime-1.1.9.dist-info/RECORD
